sistem_bancario/__init__.py
sistem_bancario/banco.py
sistem_bancario-0.0.1.dist-info/METADATA
sistem_bancario-0.0.1.dist-info/WHEEL
sistem_bancario-0.0.1.dist-info/entry_points.txt
sistem_bancario-0.0.1.dist-info/top_level.txt
sistem_bancario-0.0.1.dist-info/RECORD
