Metadata-Version: 2.4
Name: sistem_bancario
Version: 0.0.1
Summary: Sistema Bancário simples utilizando Python
Home-page: https://github.com/Beiatrixx/sistema-bancario-package
Author: Beatriz
Requires-Python: >=3.6
Dynamic: author
Dynamic: description
Dynamic: description-content-type
Dynamic: home-page
Dynamic: requires-python
Dynamic: summary
